README.md
setup.py
synapseunit.egg-info/PKG-INFO
synapseunit.egg-info/SOURCES.txt
synapseunit.egg-info/dependency_links.txt
synapseunit.egg-info/requires.txt
synapseunit.egg-info/top_level.txt
synapseunit/capabilities/__init__.py
synapseunit/capabilities/cap_ProducesAMPA.py
synapseunit/capabilities/cap_ProducesAMPAVector.py
synapseunit/scores/__init__.py
synapseunit/scores/score_RMS.py
synapseunit/tests/__init__.py
synapseunit/tests/test_STDP.py
synapseunit/tests/stimuli/STDPtest/protocol_bidirectional.json
synapseunit/tests/stimuli/STDPtest/protocol_ltd.json
synapseunit/tests/stimuli/STDPtest/protocol_ltp.json