Metadata-Version: 1.0
Name: synapseunit
Version: 0.0.2
Summary: A SciUnit library for data-driven validation testing of synaptic models.
Home-page: https://github.com/appukuttan-shailesh/SynapseUnit
Author: Justinas Dainauskas, Shailesh Appukuttan
Author-email: shailesh.appukuttan@unic.cnrs-gif.fr
License: BSD-3-Clause
Platform: UNKNOWN
